web3scout/__init__.py
web3scout/abi/__init__.py
web3scout/abi/abi_load.py
web3scout/configs/ERC20MockDecimals.json
web3scout/configs/agnostic/UniswapV2Pair.json
web3scout/configs/agnostic/UniswapV3Pool.json
web3scout/configs/erc/ERC20.json
web3scout/configs/erc/ERC20MockDecimals.json
web3scout/configs/sushi/UniswapV2Factory.json
web3scout/configs/sushi/UniswapV2Pair.json
web3scout/configs/sushi/UniswapV2Router02.json
web3scout/configs/uniswap_v3/UniswapV3Factory.json
web3scout/configs/uniswap_v3/UniswapV3Pool.json
web3scout/contract/__utils__.py
web3scout/contract/deploy.py
web3scout/contract/view.py
web3scout/data/__init__.py
web3scout/data/chain_reorganization_resolution.py
web3scout/data/filter.py
web3scout/data/pair.py
web3scout/data/reorganization_monitor.py
web3scout/data/token_details.py
web3scout/enums/__init__.py
web3scout/enums/contracts_enum.py
web3scout/enums/event_type_enum.py
web3scout/enums/init_event_enum.py
web3scout/enums/nets_enum.py
web3scout/enums/platforms_enum.py
web3scout/enums/rpcs_enum.py
web3scout/event/__init__.py
web3scout/event/burn_event.py
web3scout/event/create_event.py
web3scout/event/event.py
web3scout/event/mint_event.py
web3scout/event/swap_event.py
web3scout/event/sync_event.py
web3scout/event/transfer_event.py
web3scout/event/process/__init__.py
web3scout/event/process/read_events.py
web3scout/event/process/retrieve_events.py
web3scout/event/tools/__init__.py
web3scout/event/tools/chain_reorganization_detection.py
web3scout/event/tools/conversion.py
web3scout/event/tools/log_context.py
web3scout/event/tools/log_result.py
web3scout/event/tools/rpc_reorganization_monitor.py
web3scout/token/__init__.py
web3scout/token/token.py
web3scout/token/fetch/__init__.py
web3scout/token/fetch/fetch_token.py
web3scout/uniswap_v2/__init__.py
web3scout/uniswap_v2/fetch_pair_details.py
web3scout/utils/__init__.py
web3scout/utils/base_utils.py
web3scout/utils/connect.py
web3scout/utils/progress_update.py
web3scout-0.0.7.dist-info/licenses/LICENSE
web3scout-0.0.7.dist-info/licenses/NOTICE
web3scout-0.0.7.dist-info/METADATA
web3scout-0.0.7.dist-info/WHEEL
web3scout-0.0.7.dist-info/top_level.txt
web3scout-0.0.7.dist-info/RECORD
