Metadata-Version: 2.4
Name: Web3Scout
Version: 0.0.7
Summary: Onchain Event Framework for DeFiPy
Home-page: https://github.com/defipy-devs/web3scout
Author: icmoore
Author-email: defipy.devs@gmail.com
License: Apache-2.0
Classifier: License :: OSI Approved :: Apache Software License
Classifier: Programming Language :: Python :: 3
Classifier: Operating System :: OS Independent
Classifier: Intended Audience :: Developers
Classifier: Topic :: Software Development :: Libraries :: Python Modules
Classifier: Topic :: Scientific/Engineering :: Information Analysis
Classifier: Topic :: Internet :: WWW/HTTP :: Dynamic Content
License-File: LICENSE
License-File: NOTICE
Requires-Dist: web3
Requires-Dist: eth_abi
Requires-Dist: eth_typing
Requires-Dist: eth_tester
Requires-Dist: eth_bloom
Requires-Dist: eth_utils
Requires-Dist: web3-ethereum-defi
Requires-Dist: hexbytes
Requires-Dist: pandas
Requires-Dist: defipy>=1.0.8
Dynamic: author
Dynamic: author-email
Dynamic: classifier
Dynamic: description
Dynamic: description-content-type
Dynamic: home-page
Dynamic: license
Dynamic: license-file
Dynamic: requires-dist
Dynamic: summary
